<?xml version="1.0" encoding="utf-8" ?><dwsync><file name="adozioni_insert_main.jsp" local="-4578579860754006016" remote="-4578579857532792552" testing="0" /><file name="adozioni_insert_new.jsp" local="-4578579860754006016" remote="-4578579857532792552" testing="0" /><file name="adozioni_insert_new_anno.jsp" local="-4578579860754006016" remote="-4578579857532792552" testing="0" /><file name="adozioni_insert_new_bambino.jsp" local="-4578579860754006016" remote="-4578579857532792552" testing="0" /><file name="adozioni_main.jsp" local="-4578579860754006016" remote="-4578579857532792552" testing="0" /><file name="anagrafe_edit.jsp" local="-4578579860754006016" remote="-4578579857532792552" testing="0" /><file name="anagrafe_main.jsp" local="-4357026549770223616" remote="-4357026549770223616" testing="0" /><file name="bambini_edit.jsp" local="-4562252113081532416" remote="-4562252109860318952" testing="0" /><file name="bambini_insert_new.jsp" local="-4562252113081532416" remote="-4562252109860318952" testing="0" /><file name="bambini_main.jsp" local="-4578579860754006016" remote="-4578579857532792552" testing="0" /><file name="elenco_completo.xls" local="-4574869009010262016" remote="-4574869005789048552" testing="0" /><file name="home.jsp" local="-4493585893940002816" remote="-4493585890718789352" testing="0" /><file name="soci_edit.jsp" local="-4578579860754006016" remote="-4578579860754006016" testing="0" /><file name="soci_edit_insert.jsp" local="-4578579860754006016" remote="-4578579860754006016" testing="0" /><file name="soci_insert_main.jsp" local="-4578579860754006016" remote="-4578579860754006016" testing="0" /><file name="soci_insert_new.jsp" local="-4578579860754006016" remote="-4578579860754006016" testing="0" /><file name="soci_main.jsp" local="-4578579860754006016" remote="-4578579860754006016" testing="0" /><file name="soci_select.jsp" local="-4214371100819193856" remote="-4214371100819193856" testing="0" /><file name="stampa.jsp" local="-4578579860754006016" remote="-4578579860754006016" testing="0" /><file name="style2.css" local="-4579322031102754816" remote="-4579322031102754816" testing="0" /><file name="style_grigio.css" local="-4579322031102754816" remote="-4579322031102754816" testing="0" /><file name="style.css" local="-4357026549770223616" remote="-4357026549770223616" testing="0" /><file name="anagrafe_main_old.jsp" local="-4357403875532079104" remote="-4179017248895758244" testing="0" /><file name="style_old.css" local="-4578579860754006016" remote="-4179017248895758244" testing="0" /></dwsync>